smartdeploymiguel/__init__.py
smartdeploymiguel/smartdeploymiguel.py
smartdeploymiguel-0.1.1.dist-info/licenses/LICENSE
smartdeploymiguel-0.1.1.dist-info/METADATA
smartdeploymiguel-0.1.1.dist-info/WHEEL
smartdeploymiguel-0.1.1.dist-info/top_level.txt
smartdeploymiguel-0.1.1.dist-info/RECORD
