Metadata-Version: 2.4
Name: smartdeploymiguel
Version: 0.1.1
Summary: Data integrity and drift validation for ML pipelines using Deepchecks and MLflow.
Home-page: https://github.com/tuusuario/smartdeploymiguel
Author: Miguel Angel
Author-email: miguelsff@gmail.com
Classifier: Programming Language :: Python :: 3
Classifier: License :: OSI Approved :: MIT License
Classifier: Operating System :: OS Independent
Requires-Python: >=3.8
License-File: LICENSE
Requires-Dist: pandas==1.5.3
Requires-Dist: scikit-learn==1.1.3
Requires-Dist: mlflow==2.11.3
Requires-Dist: joblib==1.3.2
Requires-Dist: deepchecks==0.17.1
Requires-Dist: fastapi==0.111.0
Requires-Dist: uvicorn==0.19.0
Requires-Dist: ray[default]==2.9.3
Requires-Dist: python-multipart==0.0.9
Requires-Dist: pydantic==1.10.13
Requires-Dist: rich==13.7.1
Dynamic: author
Dynamic: author-email
Dynamic: classifier
Dynamic: home-page
Dynamic: license-file
Dynamic: requires-dist
Dynamic: requires-python
Dynamic: summary
